Workbook

Sheet Legenda
A1: Catálogo de indicadores previstos · painel de empresas CREA-SP (V18)
A2: Para revisar: preencha as colunas amarelas da aba Indicadores. Decisão = Manter, Ajustar ou Cortar (lista suspensa); Comentário = texto livre. A aba Resumo conta sozinha.
A3: Exemplo de preenchimento: Decisão "Ajustar" · Comentário "Trocar a rosca por barras e mostrar só empresas ativas".
A5: Como ler
A6: • Prioridade:
A7: • E = essencial;
A8: • I = importante;
A9: • C = complementar (candidato a corte).
A10: • Fonte: primeiro, a fonte em produção; depois do "·", o dado usado no protótipo:
A11: • real: dado público versionado;
A12: • demo: cenário demonstrativo;
A13: • demo derivado: fato gerado a partir do cenário, como ações e autos.
... A38: • Limite normativo vigente de empresas por responsável técnico (RT-04).

Sheet Indicadores
A1: Aba | B1: ID | C1: Indicador | D1: Cálculo | E1: Objetivo | F1: Fonte em produção | G1: Dado no protótipo | H1: Forma gráfica | I1: Prioridade | J1: Decisão | K1: Comentário
A2: Visão geral | B2: VG-01 | C2: Empresas registradas | D2: Empresas com registro ativo no corte; variação sobre o início do período | E2: Tamanho e evolução da base | F2: Cadastro PJ | G2: demo | H2: Cartão + sparkline 24 meses | I2: Essencial
A3: Visão geral | B3: VG-02 | C3: Cobertura do mercado | D3: CNPJs ativos na Receita com CNAE de engenharia e registro ativo ÷ total desses CNPJs | E3: Quanto do mercado formal está registrado | F3: Receita (CNPJ) × cadastro | G3: demo | H3: Cartão + barra de meta | I3: Essencial
A4: Visão geral | B4: VG-03 | C4: Autos de infração lavrados | D4: Autos no período; variação anual; ações fiscalizatórias e regularizações no subtítulo | E4: Intensidade da fiscalização | F4: Sistema de fiscalização | G4: demo derivado | H4: Cartão + sparkline | I4: Essencial
A5: Visão geral | B5: VG-04 | C5: Arrecadação de empresas | D5: Anuidades + multas recebidas no período; variação anual | E5: Receita vinda de pessoa jurídica | F5: Financeiro | G5: demo | H5: Cartão + sparkline | I5: Essencial
A6: Visão geral | B6: VG-05 | C6: Saldo vencido de empresas | D6: Valor vencido e não pago no corte; % de empresas inadimplentes | E6: Risco de receita e tamanho da cobrança | F6: Financeiro | G6: demo | H6: Cartão + sparkline | I6: Essencial
A7: Visão geral | B7: VG-06 | C7: ARTs de empresas | D7: ARTs registradas no período; variação anual; % de empresas com RT | E7: Atividade técnica declarada | F7: Sistema de ART | G7: demo | H7: Cartão + sparkline | I7: Importante
A8: Visão geral | B8: VG-07 | C8: Empresas com indício de irregularidade | D8: Empresas com ao menos um indício da aba Malha fina; % já com ação fiscal | E8: Tamanho do problema conhecido por cruzamento de bases | F8: Aba 4 | G8: demo | H8: Cartão + barra segmentada | I8: Importante
A9: Visão geral | B9: VG-08 | C9: Atendimento no prazo | D9: Solicitações resolvidas em até 14 dias ÷ (resolvidas + abertas com prazo vencido) | E9: Qualidade do serviço | F9: Atendimento | G9: demo | H9: Cartão + barra de meta | I9: Importante
A10: Visão geral | B10: VG-09 | C10: Mapa das regionais | D10: Indicador escolhido por GRE: empresas, cobertura, sem registro, autos, arrecadação, inadimplência, ARTs, indícios, empregos técnicos | E10: Onde cada assunto está melhor ou pior | F10: Várias | G10: demo | H10: Coroplético por GRE (municípios) + ranking ao lado | I10: Essencial
A11: Visão geral | B11: VG-10 | C11: Quadro das regionais | D11: Por GRE: empresas, tendência 24 meses, variação, cobertura, sem registro, autos, % regularizado, arrecadação, inadimplência | E11: Comparar regionais lado a lado | F11: Várias | G11: demo | H11: Tabela com barras, sparkline, setas vs. meta e cor por intensidade | I11: Essencial
A12: Visão geral | B12: VG-11 | C12: Leitura do período | D12: Frases geradas com as maiores variações e destaques de cada assunto | E12: Resumo pronto para reunião | F12: Calculado | H12: Lista de destaques + faixa rolante no topo | I12: Importante
A13: Cadastro | B13: CAD-01 | C13: Situação do registro | D13: Empresas do universo de engenharia: ativa, inativa (já registrada), nunca registrada; à parte, vistos de outro CREA | E13: Retrato da base, como no painel de profissionais | F13: Cadastro × Receita | G13: demo | H13: Rosca | I13: Essencial
A14: Cadastro | B14: CAD-02 | C14: Situação de pagamento | D14: Empresas ativas em dia × inadimplentes | E14: Saúde financeira da base | F14: Financeiro | G14: demo | H14: Rosca | I14: Essencial
A15: Cadastro | B15: CAD-03 | C15: Empresas por câmara e porte | D15: Empresas ativas por câmara e por porte (Receita) | E15: Composição da base | F15: Cadastro × Receita | G15: demo | H15: Barras empilhadas | I15: Importante
A16: Cadastro | B16: CAD-04 | C16: Mercado por câmara | D16: CNPJs de engenharia ativos por câmara, em 4 situações: registrado em dia; registrado inadimplente; sem registro, com ação; sem registro, sem ação | E16: Onde está o mercado fora do CREA | F16: Receita × cadastro × fiscalização | G16: demo | H16: Mekko (largura = tamanho do mercado) | I16: Essencial
A17: Cadastro | B17: CAD-05 | C17: Entradas e saídas por mês | D17: Entradas (espontâneas e após fiscalização) e saídas (baixa e cancelamento) por mês; linha do estoque | E17: Ritmo de crescimento e de evasão | F17: Cadastro | G17: demo | H17: Barras divergentes + linha, 24 meses | I17: Essencial
A18: Cadastro | B18: CAD-06 | C18: Ponte da base | D18: Abertura + espontâneas + após fiscalização + retornos − saídas = final | E18: Explicar a variação do período | F18: Cadastro × fiscalização | G18: demo | H18: Cascata | I18: Importante
A19: Cadastro | B19: CAD-07 | C19: Funil de conformidade | D19: Universo → registro ativo → com RT → com ART no período | E19: Onde a conformidade se perde | F19: Cadastro, RT e ART | G19: demo | H19: Sankey | I19: Importante
A20: Cadastro | B20: CAD-08 | C20: Prazo de concessão do registro | D20: Dias entre o pedido e o início do registro; mediana e P90 | E20: Agilidade para a empresa se regularizar | F20: Cadastro | G20: demo | H20: Histograma | I20: Importante
A21: Cadastro | B21: CAD-09 | C21: Base por regional | D21: Empresas ativas por GRE, mês a mês | E21: Tendência regional | F21: Cadastro | G21: demo | H21: Pequenos múltiplos, 24 meses | I21: Complementar
A22: Fiscalização | B22: FIS-01 | C22: Ações fiscalizatórias | D22: Vistorias, diligências e notificações a empresas no período; variação anual; média mensal; % por origem | E22: Produção da fiscalização | F22: Sistema de fiscalização | G22: demo derivado | H22: Cartão + sparkline | I22: Essencial
A23: Fiscalização | B23: FIS-02 | C23: Autos de infração lavrados | D23: Autos por infração: falta de registro (art. 59 da Lei 5.194/66), falta de RT (art. 6º, e), falta de ART (Lei 6.496/77); % das ações que geraram auto | E23: Atuação punitiva por tipo | F23: Idem | G23: demo derivado | H23: Cartão + barra por tipo | I23: Essencial
A24: Fiscalização | B24: FIS-03 | C24: Multas aplicadas | D24: Soma dos autos do período, por destino: paga, prazo de defesa, em julgamento, dívida ativa, cancelada | E24: Resultado financeiro e o que exige cobrança | F24: Fiscalização × financeiro | G24: demo derivado | H24: Cartão + barra segmentada | I24: Essencial
... A79: Contexto público (somente dados reais) | B79: PUB-06 | C79: Registros profissionais novos por ano | D79: Série de SP e do Brasil | E79: Tendência de entrada no Sistema | F79: Confea SIC | G79: real | H79: Barras + linha | I79: Complementar

Sheet Resumo
A1: Aba | B1: Indicadores | C1: Essencial | D1: Importante | E1: Complementar | F1: Manter | G1: Ajustar | H1: Cortar | I1: Sem decisão
A2: Visão geral | B2: =COUNTIF(Indicadores!$A$2:$A$79,A2) -> 11 | C2: =COUNTIFS(Indicadores!$A$2:$A$79,$A2,Indicadores!$I$2:$I$79,"Essencial") -> 7 | D2: =COUNTIFS(Indicadores!$A$2:$A$79,$A2,Indicadores!$I$2:$I$79,"Importante") -> 4 | E2: =COUNTIFS(Indicadores!$A$2:$A$79,$A2,Indicadores!$I$2:$I$79,"Complementar") -> 0 | F2: =COUNTIFS(Indicadores!$A$2:$A$79,$A2,Indicadores!$J$2:$J$79,"Manter") -> 0 | G2: =COUNTIFS(Indicadores!$A$2:$A$79,$A2,Indicadores!$J$2:$J$79,"Ajustar") -> 0 | H2: =COUNTIFS(Indicadores!$A$2:$A$79,$A2,Indicadores!$J$2:$J$79,"Cortar") -> 0 | I2: =B2-F2-G2-H2 -> 11
A3: Cadastro | B3: =COUNTIF(Indicadores!$A$2:$A$79,A3) -> 9 | C3: =COUNTIFS(Indicadores!$A$2:$A$79,$A3,Indicadores!$I$2:$I$79,"Essencial") -> 4 | D3: =COUNTIFS(Indicadores!$A$2:$A$79,$A3,Indicadores!$I$2:$I$79,"Importante") -> 4 | E3: =COUNTIFS(Indicadores!$A$2:$A$79,$A3,Indicadores!$I$2:$I$79,"Complementar") -> 1 | F3: =COUNTIFS(Indicadores!$A$2:$A$79,$A3,Indicadores!$J$2:$J$79,"Manter") -> 0 | G3: =COUNTIFS(Indicadores!$A$2:$A$79,$A3,Indicadores!$J$2:$J$79,"Ajustar") -> 0 | H3: =COUNTIFS(Indicadores!$A$2:$A$79,$A3,Indicadores!$J$2:$J$79,"Cortar") -> 0 | I3: =B3-F3-G3-H3 -> 9
A4: Fiscalização | B4: =COUNTIF(Indicadores!$A$2:$A$79,A4) -> 12 | C4: =COUNTIFS(Indicadores!$A$2:$A$79,$A4,Indicadores!$I$2:$I$79,"Essencial") -> 7 | D4: =COUNTIFS(Indicadores!$A$2:$A$79,$A4,Indicadores!$I$2:$I$79,"Importante") -> 4 | E4: =COUNTIFS(Indicadores!$A$2:$A$79,$A4,Indicadores!$I$2:$I$79,"Complementar") -> 1 | F4: =COUNTIFS(Indicadores!$A$2:$A$79,$A4,Indicadores!$J$2:$J$79,"Manter") -> 0 | G4: =COUNTIFS(Indicadores!$A$2:$A$79,$A4,Indicadores!$J$2:$J$79,"Ajustar") -> 0 | H4: =COUNTIFS(Indicadores!$A$2:$A$79,$A4,Indicadores!$J$2:$J$79,"Cortar") -> 0 | I4: =B4-F4-G4-H4 -> 12
A5: Malha fina (indícios por cruzamento de bases) | B5: =COUNTIF(Indicadores!$A$2:$A$79,A5) -> 9 | C5: =COUNTIFS(Indicadores!$A$2:$A$79,$A5,Indicadores!$I$2:$I$79,"Essencial") -> 3 | D5: =COUNTIFS(Indicadores!$A$2:$A$79,$A5,Indicadores!$I$2:$I$79,"Importante") -> 5 | E5: =COUNTIFS(Indicadores!$A$2:$A$79,$A5,Indicadores!$I$2:$I$79,"Complementar") -> 1 | F5: =COUNTIFS(Indicadores!$A$2:$A$79,$A5,Indicadores!$J$2:$J$79,"Manter") -> 0 | G5: =COUNTIFS(Indicadores!$A$2:$A$79,$A5,Indicadores!$J$2:$J$79,"Ajustar") -> 0 | H5: =COUNTIFS(Indicadores!$A$2:$A$79,$A5,Indicadores!$J$2:$J$79,"Cortar") -> 0 | I5: =B5-F5-G5-H5 -> 9
A6: Responsabilidade técnica, ART e certidões | B6: =COUNTIF(Indicadores!$A$2:$A$79,A6) -> 11 | C6: =COUNTIFS(Indicadores!$A$2:$A$79,$A6,Indicadores!$I$2:$I$79,"Essencial") -> 4 | D6: =COUNTIFS(Indicadores!$A$2:$A$79,$A6,Indicadores!$I$2:$I$79,"Importante") -> 5 | E6: =COUNTIFS(Indicadores!$A$2:$A$79,$A6,Indicadores!$I$2:$I$79,"Complementar") -> 2 | F6: =COUNTIFS(Indicadores!$A$2:$A$79,$A6,Indicadores!$J$2:$J$79,"Manter") -> 0 | G6: =COUNTIFS(Indicadores!$A$2:$A$79,$A6,Indicadores!$J$2:$J$79,"Ajustar") -> 0 | H6: =COUNTIFS(Indicadores!$A$2:$A$79,$A6,Indicadores!$J$2:$J$79,"Cortar") -> 0 | I6: =B6-F6-G6-H6 -> 11
A7: Receita, cobrança e orçamento | B7: =COUNTIF(Indicadores!$A$2:$A$79,A7) -> 11 | C7: =COUNTIFS(Indicadores!$A$2:$A$79,$A7,Indicadores!$I$2:$I$79,"Essencial") -> 4 | D7: =COUNTIFS(Indicadores!$A$2:$A$79,$A7,Indicadores!$I$2:$I$79,"Importante") -> 5 | E7: =COUNTIFS(Indicadores!$A$2:$A$79,$A7,Indicadores!$I$2:$I$79,"Complementar") -> 2 | F7: =COUNTIFS(Indicadores!$A$2:$A$79,$A7,Indicadores!$J$2:$J$79,"Manter") -> 0 | G7: =COUNTIFS(Indicadores!$A$2:$A$79,$A7,Indicadores!$J$2:$J$79,"Ajustar") -> 0 | H7: =COUNTIFS(Indicadores!$A$2:$A$79,$A7,Indicadores!$J$2:$J$79,"Cortar") -> 0 | I7: =B7-F7-G7-H7 -> 11
A8: Atendimento e estrutura | B8: =COUNTIF(Indicadores!$A$2:$A$79,A8) -> 9 | C8: =COUNTIFS(Indicadores!$A$2:$A$79,$A8,Indicadores!$I$2:$I$79,"Essencial") -> 1 | D8: =COUNTIFS(Indicadores!$A$2:$A$79,$A8,Indicadores!$I$2:$I$79,"Importante") -> 6 | E8: =COUNTIFS(Indicadores!$A$2:$A$79,$A8,Indicadores!$I$2:$I$79,"Complementar") -> 2 | F8: =COUNTIFS(Indicadores!$A$2:$A$79,$A8,Indicadores!$J$2:$J$79,"Manter") -> 0 | G8: =COUNTIFS(Indicadores!$A$2:$A$79,$A8,Indicadores!$J$2:$J$79,"Ajustar") -> 0 | H8: =COUNTIFS(Indicadores!$A$2:$A$79,$A8,Indicadores!$J$2:$J$79,"Cortar") -> 0 | I8: =B8-F8-G8-H8 -> 9
A9: Contexto público (somente dados reais) | B9: =COUNTIF(Indicadores!$A$2:$A$79,A9) -> 6 | C9: =COUNTIFS(Indicadores!$A$2:$A$79,$A9,Indicadores!$I$2:$I$79,"Essencial") -> 0 | D9: =COUNTIFS(Indicadores!$A$2:$A$79,$A9,Indicadores!$I$2:$I$79,"Importante") -> 3 | E9: =COUNTIFS(Indicadores!$A$2:$A$79,$A9,Indicadores!$I$2:$I$79,"Complementar") -> 3 | F9: =COUNTIFS(Indicadores!$A$2:$A$79,$A9,Indicadores!$J$2:$J$79,"Manter") -> 0 | G9: =COUNTIFS(Indicadores!$A$2:$A$79,$A9,Indicadores!$J$2:$J$79,"Ajustar") -> 0 | H9: =COUNTIFS(Indicadores!$A$2:$A$79,$A9,Indicadores!$J$2:$J$79,"Cortar") -> 0 | I9: =B9-F9-G9-H9 -> 6
A10: Total | B10: =SUM(B2:B9) -> 78 | C10: =SUM(C2:C9) -> 30 | D10: =SUM(D2:D9) -> 36 | E10: =SUM(E2:E9) -> 12 | F10: =SUM(F2:F9) -> 0 | G10: =SUM(G2:G9) -> 0 | H10: =SUM(H2:H9) -> 0 | I10: =SUM(I2:I9) -> 78
